fds/__init__.py
fds/sdk/__init__.py
fds/sdk/IDLookup/__init__.py
fds/sdk/IDLookup/api_client.py
fds/sdk/IDLookup/configuration.py
fds/sdk/IDLookup/exceptions.py
fds/sdk/IDLookup/model_utils.py
fds/sdk/IDLookup/rest.py
fds/sdk/IDLookup/api/__init__.py
fds/sdk/IDLookup/api/fact_set_id_lookup_api.py
fds/sdk/IDLookup/apis/__init__.py
fds/sdk/IDLookup/model/__init__.py
fds/sdk/IDLookup/model/datasets.py
fds/sdk/IDLookup/model/error_example.py
fds/sdk/IDLookup/model/error_response.py
fds/sdk/IDLookup/model/exclude_object.py
fds/sdk/IDLookup/model/fields_object.py
fds/sdk/IDLookup/model/filter_objects.py
fds/sdk/IDLookup/model/filters.py
fds/sdk/IDLookup/model/helper_endpoint.py
fds/sdk/IDLookup/model/helper_object.py
fds/sdk/IDLookup/model/include_object.py
fds/sdk/IDLookup/model/lookup_object.py
fds/sdk/IDLookup/model/lookup_request.py
fds/sdk/IDLookup/model/lookup_request_meta.py
fds/sdk/IDLookup/model/lookup_response.py
fds/sdk/IDLookup/model/lookup_response_meta.py
fds/sdk/IDLookup/model/lookup_response_meta_result_count.py
fds/sdk/IDLookup/model/response_details.py
fds/sdk/IDLookup/model/response_details_underlying.py
fds/sdk/IDLookup/model/values_object.py
fds/sdk/IDLookup/models/__init__.py
fds.sdk.IDLookup-1.0.2.dist-info/LICENSE
fds.sdk.IDLookup-1.0.2.dist-info/METADATA
fds.sdk.IDLookup-1.0.2.dist-info/WHEEL
fds.sdk.IDLookup-1.0.2.dist-info/top_level.txt
fds.sdk.IDLookup-1.0.2.dist-info/RECORD
